mep_tools/__init__.py
mep_tools/connectors/__init__.py
mep_tools/connectors/blueprint_pb2.py
mep_tools/connectors/blueprint_pb2.pyi
mep_tools/connectors/blueprint_pb2_grpc.py
mep_tools/connectors/chart_dispatcher_pb2.py
mep_tools/connectors/chart_dispatcher_pb2.pyi
mep_tools/connectors/chart_dispatcher_pb2_grpc.py
mep_tools/connectors/company_pb2.py
mep_tools/connectors/company_pb2.pyi
mep_tools/connectors/company_pb2_grpc.py
mep_tools/connectors/connect_portal_pb2.py
mep_tools/connectors/connect_portal_pb2.pyi
mep_tools/connectors/connect_portal_pb2_grpc.py
mep_tools/connectors/connector_pb2.py
mep_tools/connectors/connector_pb2.pyi
mep_tools/connectors/connector_pb2_grpc.py
mep_tools/connectors/metric_pb2.py
mep_tools/connectors/metric_pb2.pyi
mep_tools/connectors/metric_pb2_grpc.py
mep_tools/connectors/platform_pb2.py
mep_tools/connectors/platform_pb2.pyi
mep_tools/connectors/platform_pb2_grpc.py
mep_tools/leads/__init__.py
mep_tools/leads/lead_tracker_pb2.py
mep_tools/leads/lead_tracker_pb2.pyi
mep_tools/leads/lead_tracker_pb2_grpc.py
mep_tools/utils/__init__.py
mep_tools/utils/json_pb2.py
mep_tools/utils/json_pb2.pyi
mep_tools/utils/json_pb2_grpc.py
mep_tools-1.2.80.dist-info/METADATA
mep_tools-1.2.80.dist-info/WHEEL
mep_tools-1.2.80.dist-info/top_level.txt
mep_tools-1.2.80.dist-info/RECORD
