Metadata-Version: 2.1
Name: mep-tools
Version: 1.2.80
Summary: grpc for rep
Home-page: UNKNOWN
Author: Khai
Author-email: sarraj@marksmen.nl
License: MIT
Platform: UNKNOWN
Classifier: License :: OSI Approved :: MIT License
Requires-Dist: grpcio
Requires-Dist: grpcio-tools
Requires-Dist: protobuf
Requires-Dist: types-protobuf
